{"notifications":[{"id":226241553,"customerAddress":"Shakargarh, PK","customerCity":"Shakargarh","customerCountry":"PK","customerName":"","customerFirstName":"Zahida","customerLastName":"","order_created_at":1653625943,"status":1,"type":"sync","out_date":0,"productName":"cotton pants 240 black","show_on_product_ids":[],"productLink":"https://www.kapraymart.com/product/cotton-pants-240-black-2","image":"https://www.kapraymart.com/wp-content/uploads/2021/06/20210617_143034-300x400.jpg"},{"id":226231153,"customerAddress":"Islamabad, PK","customerCity":"Islamabad","customerCountry":"PK","customerName":"","customerFirstName":"Sumaika","customerLastName":"","order_created_at":1653518364,"status":1,"type":"sync","out_date":0,"productName":"cotton emb pants 105- black","show_on_product_ids":[],"productLink":"https://www.kapraymart.com/product/cotton-emb-pants-105-black-2","image":"https://www.kapraymart.com/wp-content/uploads/2020/09/20200915_152316.jpg"},{"id":226228960,"customerAddress":"Lahore, PK","customerCity":"Lahore","customerCountry":"PK","customerName":"","customerFirstName":"Jamila","customerLastName":"","order_created_at":1653500216,"status":1,"type":"sync","out_date":0,"productName":"Chiffon kali 3pc suit- black","show_on_product_ids":[],"productLink":"https://www.kapraymart.com/product/chiffon-kali-3pc-suit","image":"https://www.kapraymart.com/wp-content/uploads/2021/02/20210219_143643-304x400.jpg"},{"id":226228312,"customerAddress":"Rawalpindi, PK","customerCity":"Rawalpindi","customerCountry":"PK","customerName":"","customerFirstName":"Musa","customerLastName":"","order_created_at":1653494351,"status":1,"type":"sync","out_date":0,"productName":"cotton pants 145 white","show_on_product_ids":[],"productLink":"https://www.kapraymart.com/product/cotton-pants-145-white","image":"https://www.kapraymart.com/wp-content/uploads/2020/10/20201025_155125-01-364x400.jpg"},{"id":226224776,"customerAddress":"Lahore, PK","customerCity":"Lahore","customerCountry":"PK","customerName":"","customerFirstName":"Ayesha","customerLastName":"","order_created_at":1653460800,"status":1,"type":"sync","out_date":0,"productName":"Chiffon kali 3pc suit- black","show_on_product_ids":[],"productLink":"https://www.kapraymart.com/product/chiffon-kali-3pc-suit","image":"https://www.kapraymart.com/wp-content/uploads/2021/02/20210219_143643-304x400.jpg"},{"id":226222512,"customerAddress":"Karachi, PK","customerCity":"Karachi","customerCountry":"PK","customerName":"","customerFirstName":"Bilal","customerLastName":"","order_created_at":1653435872,"status":1,"type":"sync","out_date":0,"productName":"cotton pants 145 white","show_on_product_ids":[],"productLink":"https://www.kapraymart.com/product/cotton-pants-145-white","image":"https://www.kapraymart.com/wp-content/uploads/2020/10/20201025_155125-01-364x400.jpg"},{"id":226222480,"customerAddress":"Karachi, PK","customerCity":"Karachi","customerCountry":"PK","customerName":"","customerFirstName":"Tariq","customerLastName":"","order_created_at":1653435371,"status":1,"type":"sync","out_date":0,"productName":"cotton shalwar 02 white","show_on_product_ids":[],"productLink":"https://www.kapraymart.com/product/cotton-shalwar-02-white","image":"https://www.kapraymart.com/wp-content/uploads/2020/07/20200720_171427-354x400.jpg"},{"id":226222481,"customerAddress":"Karachi, PK","customerCity":"Karachi","customerCountry":"PK","customerName":"","customerFirstName":"Tariq","customerLastName":"","order_created_at":1653435371,"status":1,"type":"sync","out_date":0,"productName":"cotton pants 240 black","show_on_product_ids":[],"productLink":"https://www.kapraymart.com/product/cotton-pants-240-black-2","image":"https://www.kapraymart.com/wp-content/uploads/2021/06/20210617_143034-300x400.jpg"},{"id":226217700,"customerAddress":"Lahore, PK","customerCity":"Lahore","customerCountry":"PK","customerName":"","customerFirstName":"Mr","customerLastName":"","order_created_at":1653390882,"status":1,"type":"sync","out_date":0,"productName":"cotton shalwar 02 white","show_on_product_ids":[],"productLink":"https://www.kapraymart.com/product/cotton-shalwar-02-white","image":"https://www.kapraymart.com/wp-content/uploads/2020/07/20200720_171427-354x400.jpg"},{"id":226211450,"customerAddress":"Multan, PK","customerCity":"Multan","customerCountry":"PK","customerName":"","customerFirstName":"Ali","customerLastName":"","order_created_at":1653325237,"status":1,"type":"sync","out_date":0,"productName":"cotton emb pants 110-black","show_on_product_ids":[],"productLink":"https://www.kapraymart.com/product/cotton-emb-pants-110-black","image":"https://www.kapraymart.com/wp-content/uploads/2020/09/20200915_152419.jpg"},{"id":226211200,"customerAddress":"Karachi, PK","customerCity":"Karachi","customerCountry":"PK","customerName":"","customerFirstName":"Umair","customerLastName":"","order_created_at":1653323037,"status":1,"type":"sync","out_date":0,"productName":"cotton pants 240 black","show_on_product_ids":[],"productLink":"https://www.kapraymart.com/product/cotton-pants-240-black-2","image":"https://www.kapraymart.com/wp-content/uploads/2021/06/20210617_143034-300x400.jpg"},{"id":226208233,"customerAddress":"Lahore, PK","customerCity":"Lahore","customerCountry":"PK","customerName":"","customerFirstName":"Huma","customerLastName":"","order_created_at":1653294239,"status":1,"type":"sync","out_date":0,"productName":"cotton pants 037 white","show_on_product_ids":[],"productLink":"https://www.kapraymart.com/product/cotton-pants-037-white","image":"https://www.kapraymart.com/wp-content/uploads/2020/05/image00018-321x400.jpg"},{"id":226207339,"customerAddress":"Rawalpindi, PK","customerCity":"Rawalpindi","customerCountry":"PK","customerName":"","customerFirstName":"Nida","customerLastName":"","order_created_at":1653283284,"status":1,"type":"sync","out_date":0,"productName":"cotton shalwar 02 white","show_on_product_ids":[],"productLink":"https://www.kapraymart.com/product/cotton-shalwar-02-white","image":"https://www.kapraymart.com/wp-content/uploads/2020/07/20200720_171427-354x400.jpg"},{"id":226201587,"customerAddress":"Rawalpindi, PK","customerCity":"Rawalpindi","customerCountry":"PK","customerName":"","customerFirstName":"Adla","customerLastName":"","order_created_at":1653219643,"status":1,"type":"sync","out_date":0,"productName":"cotton shalwar 02black","show_on_product_ids":[],"productLink":"https://www.kapraymart.com/product/cotton-shalwar-02black","image":"https://www.kapraymart.com/wp-content/uploads/2020/07/20200720_171419-353x400.jpg"},{"id":226200809,"customerAddress":"peshawar, PK","customerCity":"peshawar","customerCountry":"PK","customerName":"","customerFirstName":"Tabeer","customerLastName":"","order_created_at":1653209582,"status":1,"type":"sync","out_date":0,"productName":"Chiffon kali 3pc suit- black","show_on_product_ids":[],"productLink":"https://www.kapraymart.com/product/chiffon-kali-3pc-suit","image":"https://www.kapraymart.com/wp-content/uploads/2021/02/20210219_143643-304x400.jpg"},{"id":226200276,"customerAddress":"Mianwali, PK","customerCity":"Mianwali","customerCountry":"PK","customerName":"","customerFirstName":"Tufail","customerLastName":"","order_created_at":1653202113,"status":1,"type":"sync","out_date":0,"productName":"cotton pants 037 white","show_on_product_ids":[],"productLink":"https://www.kapraymart.com/product/cotton-pants-037-white","image":"https://www.kapraymart.com/wp-content/uploads/2020/05/image00018-321x400.jpg"},{"id":226200277,"customerAddress":"Mianwali, PK","customerCity":"Mianwali","customerCountry":"PK","customerName":"","customerFirstName":"Tufail","customerLastName":"","order_created_at":1653202113,"status":1,"type":"sync","out_date":0,"productName":"cotton pants 145 black","show_on_product_ids":[],"productLink":"https://www.kapraymart.com/product/cotton-pants-145-black","image":"https://www.kapraymart.com/wp-content/uploads/2020/10/20201025_154003-01-374x400.jpg"},{"id":226198401,"customerAddress":"Lahore, PK","customerCity":"Lahore","customerCountry":"PK","customerName":"","customerFirstName":"Zainab","customerLastName":"","order_created_at":1653168898,"status":1,"type":"sync","out_date":0,"productName":"Chiffon kali 3pc suit- black","show_on_product_ids":[],"productLink":"https://www.kapraymart.com/product/chiffon-kali-3pc-suit","image":"https://www.kapraymart.com/wp-content/uploads/2021/02/20210219_143643-304x400.jpg"},{"id":226195653,"customerAddress":"Gujranwala, PK","customerCity":"Gujranwala","customerCountry":"PK","customerName":"","customerFirstName":"ramza","customerLastName":"","order_created_at":1653139459,"status":1,"type":"sync","out_date":0,"productName":"cotton pants 240 black","show_on_product_ids":[],"productLink":"https://www.kapraymart.com/product/cotton-pants-240-black-2","image":"https://www.kapraymart.com/wp-content/uploads/2021/06/20210617_143034-300x400.jpg"},{"id":226192569,"customerAddress":"Islamabad, PK","customerCity":"Islamabad","customerCountry":"PK","customerName":"","customerFirstName":"Sobia","customerLastName":"","order_created_at":1653095032,"status":1,"type":"sync","out_date":0,"productName":"cotton shalwar  02 skin","show_on_product_ids":[],"productLink":"https://www.kapraymart.com/product/cotton-shalwar-02-skin","image":"https://www.kapraymart.com/wp-content/uploads/2020/07/20200720_171456-362x400.jpg"},{"id":226191716,"customerAddress":"Lahore, PK","customerCity":"Lahore","customerCountry":"PK","customerName":"","customerFirstName":"Isha","customerLastName":"","order_created_at":1653081822,"status":1,"type":"sync","out_date":0,"productName":"cotton pants 037 white","show_on_product_ids":[],"productLink":"https://www.kapraymart.com/product/cotton-pants-037-white","image":"https://www.kapraymart.com/wp-content/uploads/2020/05/image00018-321x400.jpg"},{"id":226191471,"customerAddress":"Lahore, PK","customerCity":"Lahore","customerCountry":"PK","customerName":"","customerFirstName":"Mrs.","customerLastName":"","order_created_at":1653079175,"status":1,"type":"sync","out_date":0,"productName":"cotton emb pants 105- black","show_on_product_ids":[],"productLink":"https://www.kapraymart.com/product/cotton-emb-pants-105-black-2","image":"https://www.kapraymart.com/wp-content/uploads/2020/09/20200915_152316.jpg"},{"id":226190999,"customerAddress":"Abbottabad, PK","customerCity":"Abbottabad","customerCountry":"PK","customerName":"","customerFirstName":"Momina","customerLastName":"","order_created_at":1653074939,"status":1,"type":"sync","out_date":0,"productName":"cotton shalwar 02 white","show_on_product_ids":[],"productLink":"https://www.kapraymart.com/product/cotton-shalwar-02-white","image":"https://www.kapraymart.com/wp-content/uploads/2020/07/20200720_171427-354x400.jpg"},{"id":226187557,"customerAddress":"Islamabad, PK","customerCity":"Islamabad","customerCountry":"PK","customerName":"","customerFirstName":"Sana","customerLastName":"","order_created_at":1653041884,"status":1,"type":"sync","out_date":0,"productName":"cotton shalwar 02 white","show_on_product_ids":[],"productLink":"https://www.kapraymart.com/product/cotton-shalwar-02-white","image":"https://www.kapraymart.com/wp-content/uploads/2020/07/20200720_171427-354x400.jpg"},{"id":226187558,"customerAddress":"Islamabad, PK","customerCity":"Islamabad","customerCountry":"PK","customerName":"","customerFirstName":"Sana","customerLastName":"","order_created_at":1653041884,"status":1,"type":"sync","out_date":0,"productName":"cotton shalwar 02black","show_on_product_ids":[],"productLink":"https://www.kapraymart.com/product/cotton-shalwar-02black","image":"https://www.kapraymart.com/wp-content/uploads/2020/07/20200720_171419-353x400.jpg"},{"id":226186651,"customerAddress":"Rawalpindi, PK","customerCity":"Rawalpindi","customerCountry":"PK","customerName":"","customerFirstName":"Rabia","customerLastName":"","order_created_at":1653031228,"status":1,"type":"sync","out_date":0,"productName":"Chiffon kali 3pc suit- black","show_on_product_ids":[],"productLink":"https://www.kapraymart.com/product/chiffon-kali-3pc-suit","image":"https://www.kapraymart.com/wp-content/uploads/2021/02/20210219_143643-304x400.jpg"},{"id":226184044,"customerAddress":"Peshawar, PK","customerCity":"Peshawar","customerCountry":"PK","customerName":"","customerFirstName":"Zarka","customerLastName":"","order_created_at":1652996392,"status":1,"type":"sync","out_date":0,"productName":"cotton pants 037 white","show_on_product_ids":[],"productLink":"https://www.kapraymart.com/product/cotton-pants-037-white","image":"https://www.kapraymart.com/wp-content/uploads/2020/05/image00018-321x400.jpg"},{"id":226180633,"customerAddress":"Karachi, PK","customerCity":"Karachi","customerCountry":"PK","customerName":"","customerFirstName":"Mariam","customerLastName":"","order_created_at":1652963370,"status":1,"type":"sync","out_date":0,"productName":"cotton emb pants 110-white","show_on_product_ids":[],"productLink":"https://www.kapraymart.com/product/cotton-emb-pants-110-white","image":"https://www.kapraymart.com/wp-content/uploads/2020/09/20200915_152408.jpg"},{"id":226173877,"customerAddress":"Lahore, PK","customerCity":"Lahore","customerCountry":"PK","customerName":"","customerFirstName":"Amna","customerLastName":"","order_created_at":1652895235,"status":1,"type":"sync","out_date":0,"productName":"cotton shalwar 02 white","show_on_product_ids":[],"productLink":"https://www.kapraymart.com/product/cotton-shalwar-02-white","image":"https://www.kapraymart.com/wp-content/uploads/2020/07/20200720_171427-354x400.jpg"},{"id":226173026,"customerAddress":"Islamabad, PK","customerCity":"Islamabad","customerCountry":"PK","customerName":"","customerFirstName":"Mehak","customerLastName":"","order_created_at":1652887300,"status":1,"type":"sync","out_date":0,"productName":"Chiffon kali 3pc suit- black","show_on_product_ids":[],"productLink":"https://www.kapraymart.com/product/chiffon-kali-3pc-suit","image":"https://www.kapraymart.com/wp-content/uploads/2021/02/20210219_143643-304x400.jpg"},{"id":226170450,"customerAddress":"Karachi, PK","customerCity":"Karachi","customerCountry":"PK","customerName":"","customerFirstName":"Maryum","customerLastName":"","order_created_at":1652863369,"status":1,"type":"sync","out_date":0,"productName":"cotton emb pants 110-black","show_on_product_ids":[],"productLink":"https://www.kapraymart.com/product/cotton-emb-pants-110-black","image":"https://www.kapraymart.com/wp-content/uploads/2020/09/20200915_152419.jpg"},{"id":226169412,"customerAddress":"Islamabad, PK","customerCity":"Islamabad","customerCountry":"PK","customerName":"","customerFirstName":"Naiyma","customerLastName":"","order_created_at":1652850657,"status":1,"type":"sync","out_date":0,"productName":"cotton pants 145 white","show_on_product_ids":[],"productLink":"https://www.kapraymart.com/product/cotton-pants-145-white","image":"https://www.kapraymart.com/wp-content/uploads/2020/10/20201025_155125-01-364x400.jpg"},{"id":226169413,"customerAddress":"Islamabad, PK","customerCity":"Islamabad","customerCountry":"PK","customerName":"","customerFirstName":"Naiyma","customerLastName":"","order_created_at":1652850657,"status":1,"type":"sync","out_date":0,"productName":"cotton shalwar 02black","show_on_product_ids":[],"productLink":"https://www.kapraymart.com/product/cotton-shalwar-02black","image":"https://www.kapraymart.com/wp-content/uploads/2020/07/20200720_171419-353x400.jpg"},{"id":226166301,"customerAddress":"lahore, PK","customerCity":"lahore","customerCountry":"PK","customerName":"","customerFirstName":"Amber","customerLastName":"","order_created_at":1652813760,"status":1,"type":"sync","out_date":0,"productName":"cotton shalwar  02 skin","show_on_product_ids":[],"productLink":"https://www.kapraymart.com/product/cotton-shalwar-02-skin","image":"https://www.kapraymart.com/wp-content/uploads/2020/07/20200720_171456-362x400.jpg"},{"id":226166302,"customerAddress":"lahore, PK","customerCity":"lahore","customerCountry":"PK","customerName":"","customerFirstName":"Amber","customerLastName":"","order_created_at":1652813760,"status":1,"type":"sync","out_date":0,"productName":"cotton shalwar 02 white","show_on_product_ids":[],"productLink":"https://www.kapraymart.com/product/cotton-shalwar-02-white","image":"https://www.kapraymart.com/wp-content/uploads/2020/07/20200720_171427-354x400.jpg"},{"id":226165693,"customerAddress":"Rawalpindi, PK","customerCity":"Rawalpindi","customerCountry":"PK","customerName":"","customerFirstName":"Talha Siddiqui","customerLastName":"","order_created_at":1652808172,"status":1,"type":"sync","out_date":0,"productName":"cotton shalwar 02black","show_on_product_ids":[],"productLink":"https://www.kapraymart.com/product/cotton-shalwar-02black","image":"https://www.kapraymart.com/wp-content/uploads/2020/07/20200720_171419-353x400.jpg"},{"id":226164850,"customerAddress":"Attock, PK","customerCity":"Attock","customerCountry":"PK","customerName":"","customerFirstName":"Sehrish","customerLastName":"","order_created_at":1652800369,"status":1,"type":"sync","out_date":0,"productName":"Chiffon kali 3pc suit- black","show_on_product_ids":[],"productLink":"https://www.kapraymart.com/product/chiffon-kali-3pc-suit","image":"https://www.kapraymart.com/wp-content/uploads/2021/02/20210219_143643-304x400.jpg"},{"id":226164056,"customerAddress":"Lahore, PK","customerCity":"Lahore","customerCountry":"PK","customerName":"","customerFirstName":"Aqsa","customerLastName":"","order_created_at":1652795016,"status":1,"type":"sync","out_date":0,"productName":"Chiffon kali 3pc suit- black","show_on_product_ids":[],"productLink":"https://www.kapraymart.com/product/chiffon-kali-3pc-suit","image":"https://www.kapraymart.com/wp-content/uploads/2021/02/20210219_143643-304x400.jpg"},{"id":226162856,"customerAddress":"Lahore, PK","customerCity":"Lahore","customerCountry":"PK","customerName":"","customerFirstName":"Jia","customerLastName":"","order_created_at":1652784292,"status":1,"type":"sync","out_date":0,"productName":"cotton pants 037 white","show_on_product_ids":[],"productLink":"https://www.kapraymart.com/product/cotton-pants-037-white","image":"https://www.kapraymart.com/wp-content/uploads/2020/05/image00018-321x400.jpg"},{"id":226162857,"customerAddress":"Lahore, PK","customerCity":"Lahore","customerCountry":"PK","customerName":"","customerFirstName":"Jia","customerLastName":"","order_created_at":1652784292,"status":1,"type":"sync","out_date":0,"productName":"cotton pants 240 black","show_on_product_ids":[],"productLink":"https://www.kapraymart.com/product/cotton-pants-240-black-2","image":"https://www.kapraymart.com/wp-content/uploads/2021/06/20210617_143034-300x400.jpg"},{"id":226162410,"customerAddress":"Lahore, PK","customerCity":"Lahore","customerCountry":"PK","customerName":"","customerFirstName":"Alishba","customerLastName":"","order_created_at":1652777365,"status":1,"type":"sync","out_date":0,"productName":"Chiffon kali 3pc suit- black","show_on_product_ids":[],"productLink":"https://www.kapraymart.com/product/chiffon-kali-3pc-suit","image":"https://www.kapraymart.com/wp-content/uploads/2021/02/20210219_143643-304x400.jpg"},{"id":226161180,"customerAddress":"Lahore, PK","customerCity":"Lahore","customerCountry":"PK","customerName":"","customerFirstName":"Sara","customerLastName":"","order_created_at":1652761513,"status":1,"type":"sync","out_date":0,"productName":"cotton pants 240 black","show_on_product_ids":[],"productLink":"https://www.kapraymart.com/product/cotton-pants-240-black-2","image":"https://www.kapraymart.com/wp-content/uploads/2021/06/20210617_143034-300x400.jpg"},{"id":226157570,"customerAddress":"Jhudo, PK","customerCity":"Jhudo","customerCountry":"PK","customerName":"","customerFirstName":"Warda","customerLastName":"","order_created_at":1652719929,"status":1,"type":"sync","out_date":0,"productName":"chiffon maxi torqGreen 6623","show_on_product_ids":[],"productLink":"https://www.kapraymart.com/product/chiffon-maxi-torqgreen-6623","image":"https://www.kapraymart.com/wp-content/uploads/2022/05/20220507_114415-285x400.jpg"},{"id":226157502,"customerAddress":"Lahore, PK","customerCity":"Lahore","customerCountry":"PK","customerName":"","customerFirstName":"AMna","customerLastName":"","order_created_at":1652719466,"status":1,"type":"sync","out_date":0,"productName":"chiffon maxi torqGreen 6623","show_on_product_ids":[],"productLink":"https://www.kapraymart.com/product/chiffon-maxi-torqgreen-6623","image":"https://www.kapraymart.com/wp-content/uploads/2022/05/20220507_114415-285x400.jpg"},{"id":226157273,"customerAddress":"rawalpindi, PK","customerCity":"rawalpindi","customerCountry":"PK","customerName":"","customerFirstName":"Zoya","customerLastName":"","order_created_at":1652717447,"status":1,"type":"sync","out_date":0,"productName":"chiffon maxi torqGreen 6623","show_on_product_ids":[],"productLink":"https://www.kapraymart.com/product/chiffon-maxi-torqgreen-6623","image":"https://www.kapraymart.com/wp-content/uploads/2022/05/20220507_114415-285x400.jpg"},{"id":226157250,"customerAddress":"SIALKOT, PK","customerCity":"SIALKOT","customerCountry":"PK","customerName":"","customerFirstName":"Mazhar","customerLastName":"","order_created_at":1652717297,"status":1,"type":"sync","out_date":0,"productName":"Chiffon kali 3pc suit- black","show_on_product_ids":[],"productLink":"https://www.kapraymart.com/product/chiffon-kali-3pc-suit","image":"https://www.kapraymart.com/wp-content/uploads/2021/02/20210219_143643-304x400.jpg"},{"id":226156686,"customerAddress":"Islamabad, PK","customerCity":"Islamabad","customerCountry":"PK","customerName":"","customerFirstName":"Sonam","customerLastName":"","order_created_at":1652712584,"status":1,"type":"sync","out_date":0,"productName":"chiffon maxi torqGreen 6623","show_on_product_ids":[],"productLink":"https://www.kapraymart.com/product/chiffon-maxi-torqgreen-6623","image":"https://www.kapraymart.com/wp-content/uploads/2022/05/20220507_114415-285x400.jpg"},{"id":226156565,"customerAddress":"Lahore, PK","customerCity":"Lahore","customerCountry":"PK","customerName":"","customerFirstName":"Bareera","customerLastName":"","order_created_at":1652711408,"status":1,"type":"sync","out_date":0,"productName":"chiffon maxi torqGreen 6623","show_on_product_ids":[],"productLink":"https://www.kapraymart.com/product/chiffon-maxi-torqgreen-6623","image":"https://www.kapraymart.com/wp-content/uploads/2022/05/20220507_114415-285x400.jpg"},{"id":226156185,"customerAddress":"Islamabad, PK","customerCity":"Islamabad","customerCountry":"PK","customerName":"","customerFirstName":"Mona","customerLastName":"","order_created_at":1652708419,"status":1,"type":"sync","out_date":0,"productName":"chiffon maxi torqGreen 6623","show_on_product_ids":[],"productLink":"https://www.kapraymart.com/product/chiffon-maxi-torqgreen-6623","image":"https://www.kapraymart.com/wp-content/uploads/2022/05/20220507_114415-285x400.jpg"},{"id":226155799,"customerAddress":"Peshawar, PK","customerCity":"Peshawar","customerCountry":"PK","customerName":"","customerFirstName":"Iqbal","customerLastName":"","order_created_at":1652704481,"status":1,"type":"sync","out_date":0,"productName":"chiffon maxi torqGreen 6623","show_on_product_ids":[],"productLink":"https://www.kapraymart.com/product/chiffon-maxi-torqgreen-6623","image":"https://www.kapraymart.com/wp-content/uploads/2022/05/20220507_114415-285x400.jpg"}]}